kv_mail/__init__.py
kv_mail-0.0.2.dist-info/LICENCE.txt
kv_mail-0.0.2.dist-info/METADATA
kv_mail-0.0.2.dist-info/WHEEL
kv_mail-0.0.2.dist-info/top_level.txt
kv_mail-0.0.2.dist-info/RECORD
